setup.py
BLTrade.egg-info/PKG-INFO
BLTrade.egg-info/SOURCES.txt
BLTrade.egg-info/dependency_links.txt
BLTrade.egg-info/requires.txt
BLTrade.egg-info/top_level.txt
bltrade/__init__.py
bltrade/blback/BLBackTest.py
bltrade/blcore/__init__.py
bltrade/blcore/blfind.py
bltrade/blcore/bllog.py
bltrade/bldata/recorddata.py
bltrade/blnet/BLMailTip.py
bltrade/blnet/__init__.py
bltrade/blstrategy/BLMainStrategy.py
bltrade/blstrategy/__init__.py
bltrade/bltq/__init__.py
bltrade/bltq/blrmcore.py
bltrade/bltrade/BLTradeVersion.py
bltrade/bltrade/__init__.py
bltrade/config/bltrade.ini
bltrade/config/user.ini
bltrade/config/version.ini
bltrade/datas/orcl-1995-2014.txt
bltrade/doc/BLTrade.docx
bltrade/test/BLBackTestIndicator.py
bltrade/test/bl00.py
bltrade/test/bl01.py
bltrade/test/bl02.py
bltrade/test/bl03.py
bltrade/test/yahoo-test.py