Metadata-Version: 2.1
Name: BLTrade
Version: 0.377
Summary: BLTrade
Home-page: 
Author: Jiawenze
Author-email: s.gua@163.com
License: MIT
Keywords: BLTrade
Classifier: Development Status :: 3 - Alpha
Classifier: License :: OSI Approved :: MIT License
Classifier: Programming Language :: Python
Classifier: Intended Audience :: Developers
Classifier: Operating System :: OS Independent
Classifier: Programming Language :: Python :: 3.8
Classifier: Programming Language :: Python :: 3.9
Classifier: Programming Language :: Python :: 3.12
Requires-Dist: backtrader
